README.txt
setup.py
SmartPager_Python.egg-info/PKG-INFO
SmartPager_Python.egg-info/SOURCES.txt
SmartPager_Python.egg-info/dependency_links.txt
SmartPager_Python.egg-info/requires.txt
SmartPager_Python.egg-info/top_level.txt
smartpager/__init__.py
smartpager/utils.py
smartpager/version.py
smartpager/dispatch/__init__.py
smartpager/dispatch/base.py
smartpager/dispatch/rabbitmq.py
smartpager/dispatch/utils.py
smartpager/resources/__init__.py
smartpager/resources/models.py
smartpager/rest/__init__.py
smartpager/rest/base.py
smartpager/rest/utils.py
tests/__init__.py
tests/test_file_handler.py
tests/test_rabbit_client.py
tests/test_rest_client.py