Metadata-Version: 1.0
Name: SmartPager-Python
Version: 0.3.3
Summary: SmartPager Communications API for Python
Home-page: UNKNOWN
Author: SmartPager
Author-email: UNKNOWN
License: UNKNOWN
Keywords: smartpager,telmediq,client
Platform: UNKNOWN
